[
    {
        "label": "Left",
        "landmarks": [
            {
                "x": 0.46412187814712524,
                "y": 0.8003865480422974,
                "z": -5.4816492678355644e-08,
                "visibility": 0.0
            },
            {
                "x": 0.4780668020248413,
                "y": 0.7646558880805969,
                "z": -0.0016247262246906757,
                "visibility": 0.0
            },
            {
                "x": 0.5010872483253479,
                "y": 0.7360787987709045,
                "z": -0.008275975473225117,
                "visibility": 0.0
            },
            {
                "x": 0.5256025791168213,
                "y": 0.7230468392372131,
                "z": -0.014959622174501419,
                "visibility": 0.0
            },
            {
                "x": 0.5464777946472168,
                "y": 0.7249664664268494,
                "z": -0.020757028833031654,
                "visibility": 0.0
            },
            {
                "x": 0.5001263618469238,
                "y": 0.7417323589324951,
                "z": -0.01807149313390255,
                "visibility": 0.0
            },
            {
                "x": 0.5342423915863037,
                "y": 0.744568943977356,
                "z": -0.030262134969234467,
                "visibility": 0.0
            },
            {
                "x": 0.5337101221084595,
                "y": 0.748350977897644,
                "z": -0.036074135452508926,
                "visibility": 0.0
            },
            {
                "x": 0.5254831314086914,
                "y": 0.7487452030181885,
                "z": -0.03782008960843086,
                "visibility": 0.0
            },
            {
                "x": 0.49904918670654297,
                "y": 0.7689823508262634,
                "z": -0.02256198786199093,
                "visibility": 0.0
            },
            {
                "x": 0.5404329895973206,
                "y": 0.7730104923248291,
                "z": -0.032001882791519165,
                "visibility": 0.0
            },
            {
                "x": 0.5358062982559204,
                "y": 0.7763291597366333,
                "z": -0.03206222876906395,
                "visibility": 0.0
            },
            {
                "x": 0.5221295952796936,
                "y": 0.776623010635376,
                "z": -0.030885573476552963,
                "visibility": 0.0
            },
            {
                "x": 0.49943336844444275,
                "y": 0.7985793352127075,
                "z": -0.02656644769012928,
                "visibility": 0.0
            },
            {
                "x": 0.538529634475708,
                "y": 0.7991811037063599,
                "z": -0.03261099010705948,
                "visibility": 0.0
            },
            {
                "x": 0.532204806804657,
                "y": 0.8002565503120422,
                "z": -0.026041915640234947,
                "visibility": 0.0
            },
            {
                "x": 0.5184592008590698,
                "y": 0.7993674278259277,
                "z": -0.02072547934949398,
                "visibility": 0.0
            },
            {
                "x": 0.49950581789016724,
                "y": 0.8263406157493591,
                "z": -0.03048577345907688,
                "visibility": 0.0
            },
            {
                "x": 0.5326935052871704,
                "y": 0.8212068676948547,
                "z": -0.03179505094885826,
                "visibility": 0.0
            },
            {
                "x": 0.5254966020584106,
                "y": 0.8217998743057251,
                "z": -0.024239078164100647,
                "visibility": 0.0
            },
            {
                "x": 0.5126278400421143,
                "y": 0.823151171207428,
                "z": -0.018396474421024323,
                "visibility": 0.0
            }
        ]
    },
    {
        "label": "Right",
        "landmarks": [
            {
                "x": 0.5702571272850037,
                "y": 0.664699375629425,
                "z": -4.6812935750040197e-08,
                "visibility": 0.0
            },
            {
                "x": 0.5563719272613525,
                "y": 0.6195951700210571,
                "z": 0.006468138191848993,
                "visibility": 0.0
            },
            {
                "x": 0.5308787226676941,
                "y": 0.5940062999725342,
                "z": 0.006224756129086018,
                "visibility": 0.0
            },
            {
                "x": 0.5056092739105225,
                "y": 0.597220242023468,
                "z": 0.005569834727793932,
                "visibility": 0.0
            },
            {
                "x": 0.490717351436615,
                "y": 0.6142003536224365,
                "z": 0.0047548683360219,
                "visibility": 0.0
            },
            {
                "x": 0.5152347683906555,
                "y": 0.5909690260887146,
                "z": -0.011739023961126804,
                "visibility": 0.0
            },
            {
                "x": 0.47102612257003784,
                "y": 0.5852351188659668,
                "z": -0.013794118538498878,
                "visibility": 0.0
            },
            {
                "x": 0.46705159544944763,
                "y": 0.5979951620101929,
                "z": -0.011123254895210266,
                "visibility": 0.0
            },
            {
                "x": 0.4737641513347626,
                "y": 0.6081700921058655,
                "z": -0.008240626193583012,
                "visibility": 0.0
            },
            {
                "x": 0.5072320103645325,
                "y": 0.6205348968505859,
                "z": -0.016207223758101463,
                "visibility": 0.0
            },
            {
                "x": 0.46396076679229736,
                "y": 0.6154641509056091,
                "z": -0.014961033128201962,
                "visibility": 0.0
            },
            {
                "x": 0.45582810044288635,
                "y": 0.6208446621894836,
                "z": -0.01094535831362009,
                "visibility": 0.0
            },
            {
                "x": 0.4543169438838959,
                "y": 0.6243370175361633,
                "z": -0.009609246626496315,
                "visibility": 0.0
            },
            {
                "x": 0.5033583045005798,
                "y": 0.6503681540489197,
                "z": -0.018676547333598137,
                "visibility": 0.0
            },
            {
                "x": 0.46663516759872437,
                "y": 0.6435489654541016,
                "z": -0.015976548194885254,
                "visibility": 0.0
            },
            {
                "x": 0.4754311144351959,
                "y": 0.645094633102417,
                "z": -0.008678876794874668,
                "visibility": 0.0
            },
            {
                "x": 0.48819005489349365,
                "y": 0.6476625800132751,
                "z": -0.0053185271099209785,
                "visibility": 0.0
            },
            {
                "x": 0.5032968521118164,
                "y": 0.6783536672592163,
                "z": -0.020304568111896515,
                "visibility": 0.0
            },
            {
                "x": 0.47573235630989075,
                "y": 0.6692872643470764,
                "z": -0.016887448728084564,
                "visibility": 0.0
            },
            {
                "x": 0.4835802912712097,
                "y": 0.6679455041885376,
                "z": -0.00888845231384039,
                "visibility": 0.0
            },
            {
                "x": 0.49400269985198975,
                "y": 0.6692761778831482,
                "z": -0.003644493641331792,
                "visibility": 0.0
            }
        ]
    }
]