[
    {
        "label": "Left",
        "landmarks": [
            {
                "x": 0.4162222146987915,
                "y": 0.6960441470146179,
                "z": 7.593178708020787e-08,
                "visibility": 0.0
            },
            {
                "x": 0.4414559006690979,
                "y": 0.6849004030227661,
                "z": 0.003975252620875835,
                "visibility": 0.0
            },
            {
                "x": 0.4575275778770447,
                "y": 0.6528775691986084,
                "z": 0.004871681332588196,
                "visibility": 0.0
            },
            {
                "x": 0.4669201076030731,
                "y": 0.6314916014671326,
                "z": 0.0036219919566065073,
                "visibility": 0.0
            },
            {
                "x": 0.47607553005218506,
                "y": 0.6160061955451965,
                "z": 0.001596017275005579,
                "visibility": 0.0
            },
            {
                "x": 0.4640105366706848,
                "y": 0.6207883358001709,
                "z": 0.0012522393371909857,
                "visibility": 0.0
            },
            {
                "x": 0.48027512431144714,
                "y": 0.5893194079399109,
                "z": -0.0055129933170974255,
                "visibility": 0.0
            },
            {
                "x": 0.4918622076511383,
                "y": 0.566290557384491,
                "z": -0.011145354248583317,
                "visibility": 0.0
            },
            {
                "x": 0.5008058547973633,
                "y": 0.5467101335525513,
                "z": -0.01590971276164055,
                "visibility": 0.0
            },
            {
                "x": 0.46032091975212097,
                "y": 0.6201938390731812,
                "z": -0.007171067874878645,
                "visibility": 0.0
            },
            {
                "x": 0.4787146747112274,
                "y": 0.5835614800453186,
                "z": -0.013539337553083897,
                "visibility": 0.0
            },
            {
                "x": 0.49220532178878784,
                "y": 0.5578121542930603,
                "z": -0.019955972209572792,
                "visibility": 0.0
            },
            {
                "x": 0.502781093120575,
                "y": 0.5347098112106323,
                "z": -0.02522209845483303,
                "visibility": 0.0
            },
            {
                "x": 0.4532927870750427,
                "y": 0.6249628067016602,
                "z": -0.015876365825533867,
                "visibility": 0.0
            },
            {
                "x": 0.4705081582069397,
                "y": 0.590969979763031,
                "z": -0.02238197810947895,
                "visibility": 0.0
            },
            {
                "x": 0.48165053129196167,
                "y": 0.5694090127944946,
                "z": -0.028226831927895546,
                "visibility": 0.0
            },
            {
                "x": 0.4902801215648651,
                "y": 0.5490403175354004,
                "z": -0.03322961926460266,
                "visibility": 0.0
            },
            {
                "x": 0.4444935619831085,
                "y": 0.6347385048866272,
                "z": -0.024346867576241493,
                "visibility": 0.0
            },
            {
                "x": 0.4523741900920868,
                "y": 0.6155458092689514,
                "z": -0.03178206458687782,
                "visibility": 0.0
            },
            {
                "x": 0.4590025246143341,
                "y": 0.5994390249252319,
                "z": -0.03644861280918121,
                "visibility": 0.0
            },
            {
                "x": 0.46451935172080994,
                "y": 0.5843235850334167,
                "z": -0.04024874418973923,
                "visibility": 0.0
            }
        ]
    },
    {
        "label": "Left",
        "landmarks": [
            {
                "x": 0.6528878211975098,
                "y": 0.6975191831588745,
                "z": 6.61370194166011e-08,
                "visibility": 0.0
            },
            {
                "x": 0.6397196650505066,
                "y": 0.6616195440292358,
                "z": 0.004010614939033985,
                "visibility": 0.0
            },
            {
                "x": 0.6225409507751465,
                "y": 0.6242501735687256,
                "z": 0.002223955001682043,
                "visibility": 0.0
            },
            {
                "x": 0.6124205589294434,
                "y": 0.5966408252716064,
                "z": -0.0006962218903936446,
                "visibility": 0.0
            },
            {
                "x": 0.6068957448005676,
                "y": 0.574360191822052,
                "z": -0.004543551709502935,
                "visibility": 0.0
            },
            {
                "x": 0.6166102886199951,
                "y": 0.6067137122154236,
                "z": -0.012089744210243225,
                "visibility": 0.0
            },
            {
                "x": 0.5926426649093628,
                "y": 0.5710216760635376,
                "z": -0.02269953489303589,
                "visibility": 0.0
            },
            {
                "x": 0.5770043134689331,
                "y": 0.547810435295105,
                "z": -0.029191602021455765,
                "visibility": 0.0
            },
            {
                "x": 0.5647993087768555,
                "y": 0.5284055471420288,
                "z": -0.03370171785354614,
                "visibility": 0.0
            },
            {
                "x": 0.6179838180541992,
                "y": 0.6167569160461426,
                "z": -0.0209076926112175,
                "visibility": 0.0
            },
            {
                "x": 0.5915552377700806,
                "y": 0.5790184736251831,
                "z": -0.030647385865449905,
                "visibility": 0.0
            },
            {
                "x": 0.574547529220581,
                "y": 0.5547502636909485,
                "z": -0.03722360357642174,
                "visibility": 0.0
            },
            {
                "x": 0.5608658194541931,
                "y": 0.5338341593742371,
                "z": -0.04253470525145531,
                "visibility": 0.0
            },
            {
                "x": 0.6195532083511353,
                "y": 0.6334599852561951,
                "z": -0.028900276869535446,
                "visibility": 0.0
            },
            {
                "x": 0.5946799516677856,
                "y": 0.6000356078147888,
                "z": -0.037963174283504486,
                "visibility": 0.0
            },
            {
                "x": 0.5791418552398682,
                "y": 0.5781020522117615,
                "z": -0.043672896921634674,
                "visibility": 0.0
            },
            {
                "x": 0.567063570022583,
                "y": 0.5591874718666077,
                "z": -0.048257336020469666,
                "visibility": 0.0
            },
            {
                "x": 0.6212891340255737,
                "y": 0.6557489037513733,
                "z": -0.036120668053627014,
                "visibility": 0.0
            },
            {
                "x": 0.603519082069397,
                "y": 0.6362068057060242,
                "z": -0.0447920598089695,
                "visibility": 0.0
            },
            {
                "x": 0.5921390056610107,
                "y": 0.6214977502822876,
                "z": -0.04878091439604759,
                "visibility": 0.0
            },
            {
                "x": 0.5823753476142883,
                "y": 0.607166051864624,
                "z": -0.05193709954619408,
                "visibility": 0.0
            }
        ]
    }
]