[
    {
        "label": "Right",
        "landmarks": [
            {
                "x": 0.6909273266792297,
                "y": 0.685441792011261,
                "z": -9.855340721287575e-08,
                "visibility": 0.0
            },
            {
                "x": 0.7071242332458496,
                "y": 0.6394655704498291,
                "z": 0.0015431265346705914,
                "visibility": 0.0
            },
            {
                "x": 0.7144458889961243,
                "y": 0.590002715587616,
                "z": -0.0012139035388827324,
                "visibility": 0.0
            },
            {
                "x": 0.7203748822212219,
                "y": 0.5488305687904358,
                "z": -0.005877883639186621,
                "visibility": 0.0
            },
            {
                "x": 0.7379463911056519,
                "y": 0.5284830331802368,
                "z": -0.011134002357721329,
                "visibility": 0.0
            },
            {
                "x": 0.6821403503417969,
                "y": 0.5729372501373291,
                "z": -0.001015037065371871,
                "visibility": 0.0
            },
            {
                "x": 0.6628748774528503,
                "y": 0.550009548664093,
                "z": -0.0041243829764425755,
                "visibility": 0.0
            },
            {
                "x": 0.6647145748138428,
                "y": 0.5636574029922485,
                "z": -0.007236352190375328,
                "visibility": 0.0
            },
            {
                "x": 0.673175573348999,
                "y": 0.5801203846931458,
                "z": -0.008594040758907795,
                "visibility": 0.0
            },
            {
                "x": 0.6617667078971863,
                "y": 0.5900527238845825,
                "z": -0.005019561853259802,
                "visibility": 0.0
            },
            {
                "x": 0.6440691351890564,
                "y": 0.5646944046020508,
                "z": -0.00659421319141984,
                "visibility": 0.0
            },
            {
                "x": 0.6468966007232666,
                "y": 0.5764062404632568,
                "z": -0.009518498554825783,
                "visibility": 0.0
            },
            {
                "x": 0.6552312970161438,
                "y": 0.5917814373970032,
                "z": -0.012236014939844608,
                "visibility": 0.0
            },
            {
                "x": 0.6441293358802795,
                "y": 0.6097510457038879,
                "z": -0.008572036400437355,
                "visibility": 0.0
            },
            {
                "x": 0.6274350881576538,
                "y": 0.581271767616272,
                "z": -0.009985209442675114,
                "visibility": 0.0
            },
            {
                "x": 0.6306427121162415,
                "y": 0.5904942750930786,
                "z": -0.011254723183810711,
                "visibility": 0.0
            },
            {
                "x": 0.6400347948074341,
                "y": 0.6049211025238037,
                "z": -0.01297345757484436,
                "visibility": 0.0
            },
            {
                "x": 0.6291279196739197,
                "y": 0.6303266882896423,
                "z": -0.011761048808693886,
                "visibility": 0.0
            },
            {
                "x": 0.6025156378746033,
                "y": 0.6113274693489075,
                "z": -0.011461427435278893,
                "visibility": 0.0
            },
            {
                "x": 0.5830446481704712,
                "y": 0.6008408665657043,
                "z": -0.011475320905447006,
                "visibility": 0.0
            },
            {
                "x": 0.5681377649307251,
                "y": 0.5908635854721069,
                "z": -0.012327582575380802,
                "visibility": 0.0
            }
        ]
    },
    {
        "label": "Left",
        "landmarks": [
            {
                "x": 0.3605268895626068,
                "y": 0.6697150468826294,
                "z": -1.417564732264509e-07,
                "visibility": 0.0
            },
            {
                "x": 0.350516140460968,
                "y": 0.6177186369895935,
                "z": -0.00014344304508995265,
                "visibility": 0.0
            },
            {
                "x": 0.3541628420352936,
                "y": 0.567039430141449,
                "z": -0.003973691258579493,
                "visibility": 0.0
            },
            {
                "x": 0.3558817207813263,
                "y": 0.5267243981361389,
                "z": -0.008001857437193394,
                "visibility": 0.0
            },
            {
                "x": 0.34257277846336365,
                "y": 0.5051366686820984,
                "z": -0.010385312139987946,
                "visibility": 0.0
            },
            {
                "x": 0.3818962275981903,
                "y": 0.5542911887168884,
                "z": -0.007528132293373346,
                "visibility": 0.0
            },
            {
                "x": 0.41184258460998535,
                "y": 0.5449597835540771,
                "z": -0.010072642005980015,
                "visibility": 0.0
            },
            {
                "x": 0.4064582884311676,
                "y": 0.560981273651123,
                "z": -0.009006073698401451,
                "visibility": 0.0
            },
            {
                "x": 0.3951736390590668,
                "y": 0.5703372955322266,
                "z": -0.008068854920566082,
                "visibility": 0.0
            },
            {
                "x": 0.3999997675418854,
                "y": 0.5766760110855103,
                "z": -0.010692019946873188,
                "visibility": 0.0
            },
            {
                "x": 0.42562681436538696,
                "y": 0.5634888410568237,
                "z": -0.011434396728873253,
                "visibility": 0.0
            },
            {
                "x": 0.4198175370693207,
                "y": 0.5769912600517273,
                "z": -0.009111419320106506,
                "visibility": 0.0
            },
            {
                "x": 0.4101160168647766,
                "y": 0.5865322351455688,
                "z": -0.00854397565126419,
                "visibility": 0.0
            },
            {
                "x": 0.41567403078079224,
                "y": 0.6005545258522034,
                "z": -0.013312342576682568,
                "visibility": 0.0
            },
            {
                "x": 0.43845486640930176,
                "y": 0.583278238773346,
                "z": -0.01447165384888649,
                "visibility": 0.0
            },
            {
                "x": 0.43298420310020447,
                "y": 0.593763530254364,
                "z": -0.010382819920778275,
                "visibility": 0.0
            },
            {
                "x": 0.42311611771583557,
                "y": 0.6019439697265625,
                "z": -0.008210797794163227,
                "visibility": 0.0
            },
            {
                "x": 0.428292840719223,
                "y": 0.6235756874084473,
                "z": -0.0155801298096776,
                "visibility": 0.0
            },
            {
                "x": 0.45425206422805786,
                "y": 0.5995721817016602,
                "z": -0.016088539734482765,
                "visibility": 0.0
            },
            {
                "x": 0.4699975550174713,
                "y": 0.5877111554145813,
                "z": -0.013780681416392326,
                "visibility": 0.0
            },
            {
                "x": 0.48216429352760315,
                "y": 0.5750627517700195,
                "z": -0.012365253642201424,
                "visibility": 0.0
            }
        ]
    }
]