[
    {
        "label": "Right",
        "landmarks": [
            {
                "x": 0.46807557344436646,
                "y": 0.7802091240882874,
                "z": 2.5690150096124853e-07,
                "visibility": 0.0
            },
            {
                "x": 0.46392080187797546,
                "y": 0.7355008721351624,
                "z": -0.011441852897405624,
                "visibility": 0.0
            },
            {
                "x": 0.4412083625793457,
                "y": 0.7018125653266907,
                "z": -0.014042731374502182,
                "visibility": 0.0
            },
            {
                "x": 0.417543888092041,
                "y": 0.6846233010292053,
                "z": -0.01398230530321598,
                "visibility": 0.0
            },
            {
                "x": 0.4018052816390991,
                "y": 0.6722658276557922,
                "z": -0.013161158189177513,
                "visibility": 0.0
            },
            {
                "x": 0.3955249786376953,
                "y": 0.7337232232093811,
                "z": -0.005291210953146219,
                "visibility": 0.0
            },
            {
                "x": 0.3770628869533539,
                "y": 0.7071820497512817,
                "z": -0.006076405290514231,
                "visibility": 0.0
            },
            {
                "x": 0.37107330560684204,
                "y": 0.6870681643486023,
                "z": -0.008787061087787151,
                "visibility": 0.0
            },
            {
                "x": 0.36930277943611145,
                "y": 0.6715136766433716,
                "z": -0.011010323651134968,
                "visibility": 0.0
            },
            {
                "x": 0.39221760630607605,
                "y": 0.7588186264038086,
                "z": 0.00034587792470119894,
                "visibility": 0.0
            },
            {
                "x": 0.375099241733551,
                "y": 0.7331950068473816,
                "z": 0.0011431495659053326,
                "visibility": 0.0
            },
            {
                "x": 0.37006184458732605,
                "y": 0.7140352725982666,
                "z": -0.0003069452359341085,
                "visibility": 0.0
            },
            {
                "x": 0.36750584840774536,
                "y": 0.6981139183044434,
                "z": -0.0020932243205606937,
                "visibility": 0.0
            },
            {
                "x": 0.39504554867744446,
                "y": 0.7777884006500244,
                "z": 0.005256030708551407,
                "visibility": 0.0
            },
            {
                "x": 0.37965673208236694,
                "y": 0.7543149590492249,
                "z": 0.005635104142129421,
                "visibility": 0.0
            },
            {
                "x": 0.3749397397041321,
                "y": 0.7369289398193359,
                "z": 0.006798479240387678,
                "visibility": 0.0
            },
            {
                "x": 0.3723900318145752,
                "y": 0.722567081451416,
                "z": 0.00709387706592679,
                "visibility": 0.0
            },
            {
                "x": 0.40129294991493225,
                "y": 0.7909386157989502,
                "z": 0.00907178409397602,
                "visibility": 0.0
            },
            {
                "x": 0.38521796464920044,
                "y": 0.7720320224761963,
                "z": 0.00969141535460949,
                "visibility": 0.0
            },
            {
                "x": 0.37929487228393555,
                "y": 0.7580862045288086,
                "z": 0.012382234446704388,
                "visibility": 0.0
            },
            {
                "x": 0.376250684261322,
                "y": 0.7468634843826294,
                "z": 0.014710742980241776,
                "visibility": 0.0
            }
        ]
    },
    {
        "label": "Left",
        "landmarks": [
            {
                "x": 0.33780598640441895,
                "y": 0.5865238904953003,
                "z": 1.0741096900801494e-07,
                "visibility": 0.0
            },
            {
                "x": 0.31896835565567017,
                "y": 0.5458570122718811,
                "z": 0.0053946576081216335,
                "visibility": 0.0
            },
            {
                "x": 0.3187596797943115,
                "y": 0.5051714181900024,
                "z": 0.008627533912658691,
                "visibility": 0.0
            },
            {
                "x": 0.32411158084869385,
                "y": 0.47512388229370117,
                "z": 0.010520461946725845,
                "visibility": 0.0
            },
            {
                "x": 0.31892478466033936,
                "y": 0.45472198724746704,
                "z": 0.011756754480302334,
                "visibility": 0.0
            },
            {
                "x": 0.34461212158203125,
                "y": 0.46412894129753113,
                "z": 0.005119072273373604,
                "visibility": 0.0
            },
            {
                "x": 0.35192522406578064,
                "y": 0.4177231788635254,
                "z": 0.002371154958382249,
                "visibility": 0.0
            },
            {
                "x": 0.35787901282310486,
                "y": 0.39038321375846863,
                "z": 0.00035163346910849214,
                "visibility": 0.0
            },
            {
                "x": 0.3631673753261566,
                "y": 0.3702940046787262,
                "z": -0.0009353483328595757,
                "visibility": 0.0
            },
            {
                "x": 0.3649139404296875,
                "y": 0.47040072083473206,
                "z": -0.0016134778270497918,
                "visibility": 0.0
            },
            {
                "x": 0.3819967210292816,
                "y": 0.4192712604999542,
                "z": -0.004019845277070999,
                "visibility": 0.0
            },
            {
                "x": 0.39227843284606934,
                "y": 0.3883780241012573,
                "z": -0.0069334120489656925,
                "visibility": 0.0
            },
            {
                "x": 0.4006423056125641,
                "y": 0.3654358685016632,
                "z": -0.008702004328370094,
                "visibility": 0.0
            },
            {
                "x": 0.3816627264022827,
                "y": 0.4866143763065338,
                "z": -0.008488737978041172,
                "visibility": 0.0
            },
            {
                "x": 0.40058961510658264,
                "y": 0.441596657037735,
                "z": -0.01319095864892006,
                "visibility": 0.0
            },
            {
                "x": 0.4124757647514343,
                "y": 0.4140394628047943,
                "z": -0.018171418458223343,
                "visibility": 0.0
            },
            {
                "x": 0.42144280672073364,
                "y": 0.391923189163208,
                "z": -0.021352989599108696,
                "visibility": 0.0
            },
            {
                "x": 0.39487224817276,
                "y": 0.5100090503692627,
                "z": -0.014675703831017017,
                "visibility": 0.0
            },
            {
                "x": 0.41579607129096985,
                "y": 0.4824535548686981,
                "z": -0.01932518184185028,
                "visibility": 0.0
            },
            {
                "x": 0.42844358086586,
                "y": 0.46523773670196533,
                "z": -0.02147691138088703,
                "visibility": 0.0
            },
            {
                "x": 0.4388836622238159,
                "y": 0.4496227502822876,
                "z": -0.022544866427779198,
                "visibility": 0.0
            }
        ]
    }
]