[
    {
        "label": "Right",
        "landmarks": [
            {
                "x": 0.47367551922798157,
                "y": 0.7791582345962524,
                "z": 2.1275984352087107e-07,
                "visibility": 0.0
            },
            {
                "x": 0.46925726532936096,
                "y": 0.7325633764266968,
                "z": -0.009429289028048515,
                "visibility": 0.0
            },
            {
                "x": 0.4455888569355011,
                "y": 0.6997811794281006,
                "z": -0.010333734564483166,
                "visibility": 0.0
            },
            {
                "x": 0.42181605100631714,
                "y": 0.6842123866081238,
                "z": -0.008861873298883438,
                "visibility": 0.0
            },
            {
                "x": 0.407112717628479,
                "y": 0.6706122756004333,
                "z": -0.006492124404758215,
                "visibility": 0.0
            },
            {
                "x": 0.40199023485183716,
                "y": 0.7285425066947937,
                "z": -0.0038902319502085447,
                "visibility": 0.0
            },
            {
                "x": 0.3820299208164215,
                "y": 0.7038415670394897,
                "z": -0.004075070843100548,
                "visibility": 0.0
            },
            {
                "x": 0.3776542544364929,
                "y": 0.6841262578964233,
                "z": -0.00594756193459034,
                "visibility": 0.0
            },
            {
                "x": 0.37760868668556213,
                "y": 0.6680243015289307,
                "z": -0.007547507528215647,
                "visibility": 0.0
            },
            {
                "x": 0.39802086353302,
                "y": 0.7537791132926941,
                "z": 0.0012341478141024709,
                "visibility": 0.0
            },
            {
                "x": 0.38078373670578003,
                "y": 0.7280881404876709,
                "z": 0.0032090339809656143,
                "visibility": 0.0
            },
            {
                "x": 0.37775522470474243,
                "y": 0.7083746790885925,
                "z": 0.0028712486382573843,
                "visibility": 0.0
            },
            {
                "x": 0.377858966588974,
                "y": 0.6919037699699402,
                "z": 0.0016336998669430614,
                "visibility": 0.0
            },
            {
                "x": 0.40086987614631653,
                "y": 0.7732055187225342,
                "z": 0.0057380604557693005,
                "visibility": 0.0
            },
            {
                "x": 0.3853437602519989,
                "y": 0.7496163249015808,
                "z": 0.0068871090188622475,
                "visibility": 0.0
            },
            {
                "x": 0.3826046586036682,
                "y": 0.7313321232795715,
                "z": 0.00783174391835928,
                "visibility": 0.0
            },
            {
                "x": 0.38272756338119507,
                "y": 0.7159014940261841,
                "z": 0.007774582132697105,
                "visibility": 0.0
            },
            {
                "x": 0.40713047981262207,
                "y": 0.786961019039154,
                "z": 0.009322221390902996,
                "visibility": 0.0
            },
            {
                "x": 0.39117345213890076,
                "y": 0.7679904103279114,
                "z": 0.010297974571585655,
                "visibility": 0.0
            },
            {
                "x": 0.38684120774269104,
                "y": 0.7530856132507324,
                "z": 0.012686553411185741,
                "visibility": 0.0
            },
            {
                "x": 0.3860016465187073,
                "y": 0.7411239743232727,
                "z": 0.01468554325401783,
                "visibility": 0.0
            }
        ]
    },
    {
        "label": "Left",
        "landmarks": [
            {
                "x": 0.3437645435333252,
                "y": 0.5731061100959778,
                "z": 8.4416114987107e-08,
                "visibility": 0.0
            },
            {
                "x": 0.32192784547805786,
                "y": 0.5345686674118042,
                "z": 0.005469183437526226,
                "visibility": 0.0
            },
            {
                "x": 0.3183215856552124,
                "y": 0.49836841225624084,
                "z": 0.007921988144516945,
                "visibility": 0.0
            },
            {
                "x": 0.32182642817497253,
                "y": 0.4704394042491913,
                "z": 0.008793702349066734,
                "visibility": 0.0
            },
            {
                "x": 0.31996068358421326,
                "y": 0.45314300060272217,
                "z": 0.009031892754137516,
                "visibility": 0.0
            },
            {
                "x": 0.3444616496562958,
                "y": 0.453877329826355,
                "z": 0.0067902919836342335,
                "visibility": 0.0
            },
            {
                "x": 0.34981533885002136,
                "y": 0.41306477785110474,
                "z": 0.004689077381044626,
                "visibility": 0.0
            },
            {
                "x": 0.3546544015407562,
                "y": 0.3901258707046509,
                "z": 0.002186666941270232,
                "visibility": 0.0
            },
            {
                "x": 0.3590531647205353,
                "y": 0.3728225827217102,
                "z": 0.00021125964121893048,
                "visibility": 0.0
            },
            {
                "x": 0.36461833119392395,
                "y": 0.45833951234817505,
                "z": 1.0255153938487638e-05,
                "visibility": 0.0
            },
            {
                "x": 0.3787158727645874,
                "y": 0.4091287851333618,
                "z": -0.001445499248802662,
                "visibility": 0.0
            },
            {
                "x": 0.3873014450073242,
                "y": 0.38111791014671326,
                "z": -0.004118838347494602,
                "visibility": 0.0
            },
            {
                "x": 0.3944973051548004,
                "y": 0.36036479473114014,
                "z": -0.006122741848230362,
                "visibility": 0.0
            },
            {
                "x": 0.38157305121421814,
                "y": 0.4732477366924286,
                "z": -0.007019259966909885,
                "visibility": 0.0
            },
            {
                "x": 0.39616674184799194,
                "y": 0.42620667815208435,
                "z": -0.010677789337933064,
                "visibility": 0.0
            },
            {
                "x": 0.40493690967559814,
                "y": 0.39957278966903687,
                "z": -0.014482077211141586,
                "visibility": 0.0
            },
            {
                "x": 0.41152334213256836,
                "y": 0.3780958652496338,
                "z": -0.017164118587970734,
                "visibility": 0.0
            },
            {
                "x": 0.3959980905056,
                "y": 0.496568500995636,
                "z": -0.01347377896308899,
                "visibility": 0.0
            },
            {
                "x": 0.4135730266571045,
                "y": 0.46476706862449646,
                "z": -0.01700534299015999,
                "visibility": 0.0
            },
            {
                "x": 0.42409461736679077,
                "y": 0.4455024003982544,
                "z": -0.018008364364504814,
                "visibility": 0.0
            },
            {
                "x": 0.43258583545684814,
                "y": 0.42748188972473145,
                "z": -0.018461283296346664,
                "visibility": 0.0
            }
        ]
    }
]